README.md
setup.py
yamm/__init__.py
yamm/chain.py
yamm.egg-info/PKG-INFO
yamm.egg-info/SOURCES.txt
yamm.egg-info/dependency_links.txt
yamm.egg-info/top_level.txt