Metadata-Version: 1.2
Name: yamm
Version: 0.0.1
Summary: yet another markov module
Home-page: https://github.com/inkeye/yamm
Author: Tim Pauli <tim.pauli@folkwang-uni.de>, Levin Zimmermann <levin-eric.zimmermann@folkwang-uni.de>
Author-email: UNKNOWN
License: GPL
Platform: UNKNOWN
Requires-Python: >=3.6
